temporal_lib/__init__.py
temporal_lib/calendar.py
temporal_lib/core.py
temporal_lib/tlib_date.py
temporal_lib/tlib_timezone.py
temporal_lib/tlib_types.py
temporal_lib/tlib_week.py
temporal_lib/tlib_weekday.py
temporal_lib/tlib_year.py
temporal_lib/cron/__init__.py
temporal_lib-0.1.1.dist-info/LICENSE
temporal_lib-0.1.1.dist-info/METADATA
temporal_lib-0.1.1.dist-info/WHEEL
temporal_lib-0.1.1.dist-info/top_level.txt
temporal_lib-0.1.1.dist-info/RECORD
