Metadata-Version: 2.2
Name: temporal-lib
Version: 0.1.1
Summary: A library for working with datetime and other temporal concepts.
Author-email: Datahenge LLC <brian@datahenge.com>
License: MIT
Keywords: datetime,cron
Classifier: Programming Language :: Python :: 3
Requires-Python: >=3.9
License-File: LICENSE
Requires-Dist: cron-converter
Requires-Dist: cron-descriptor
Requires-Dist: local-crontab
Requires-Dist: python-dateutil>=2.8.2
Requires-Dist: toml>=0.10.2
Requires-Dist: tzlocal>=4.2
Provides-Extra: dev
Requires-Dist: build~=0.10.0; extra == "dev"
Requires-Dist: flake8>=4.0.1; extra == "dev"
Requires-Dist: flake8-tabs; extra == "dev"
Requires-Dist: ipython~=8.11.0; extra == "dev"
Requires-Dist: mypy~=1.1.1; extra == "dev"
Requires-Dist: pylint>=2.12.2; extra == "dev"
Requires-Dist: pytest>=7.2.2; extra == "dev"
Requires-Dist: twine>=4.0.2; extra == "dev"
